{
    "Version": "2012-10-17",
    "Statement": [
        {
            "Action": [
                "dynamodb:GetItem"
            ],
            "Effect": "Allow",
            "Resource": "arn:aws:dynamodb:us-east-1:024700040865:table/SampleAuthUsers"
        },
        {
            "Effect": "Allow",
            "Action": [
                "cognito-identity:GetOpenIdTokenForDeveloperIdentity"
            ],
            "Resource": "arn:aws:cognito-identity:us-east-1:024700040865:identitypool/us-east-1:3909a295-f5f8-4d6b-97ea-994ed4d324dd"
        },
        {
            "Sid": "",
            "Resource": "*",
            "Action": [
                "logs:*"
            ],
            "Effect": "Allow"
        }
    ]
}
